<?xml version='1.0' encoding='utf-8'?>
<oai_dc:dc xmlns:dc="http://purl.org/dc/elements/1.1/" xmlns:oai_dc="http://www.openarchives.org/OAI/2.0/oai_dc/" xmlns:xsi="http://www.w3.org/2001/XMLSchema-instance" xsi:schemaLocation="http://www.openarchives.org/OAI/2.0/oai_dc/ http://www.openarchives.org/OAI/2.0/oai_dc.xsd">
  <dc:creators>|uma (XIII)</dc:creators>
  <dc:date>2020-09-12</dc:date>
  <dc:description>When one of the !kun dies, the people dig a grave and put the dead person into it. The body is covered in earth and the grave is filled in. A tree is cut down and laid over the grave. |uma relates the death of one of his relatives who was killed by an arrow. His people put the relative into the earth and the women cried for him. If a stranger is killed they do not bury him. The account includes mention of how tobacco is shared with a stranger. If the man returns with none to share he is killed. 1) p.10 262v: |uma from personal observation, 2) p.10 267v: the ||'i thorn-tree, 3) p.10 269v: the !kun do not refuse a stranger tobacco; when the person returns he brings tobacco for them in return; if the man returns without tobacco he is killed, 4) See also Dress after death and Burial and Burial (another account), 5) This story is found in Book XIII &amp; XIV-1.</dc:description>
  <dc:format>Unqualified Dublin Core</dc:format>
  <dc:identifier>http://pumbaa.cs.uct.ac.za/~balnew/metadata/stories/1114</dc:identifier>
  <dc:publisher>Lucy Lloyd</dc:publisher>
  <dc:rights>CC-BY-NC-ND</dc:rights>
  <dc:source>Lucy Lloyd</dc:source>
  <dc:subject>Lucy Lloyd !kun notebooks</dc:subject>
  <dc:title>Burial; also avenging a death</dc:title>
  <dc:type>story</dc:type>
</oai_dc:dc>
