<?xml version='1.0' encoding='utf-8'?>
<oai_dc:dc xmlns:dc="http://purl.org/dc/elements/1.1/" xmlns:oai_dc="http://www.openarchives.org/OAI/2.0/oai_dc/" xmlns:xsi="http://www.w3.org/2001/XMLSchema-instance" xsi:schemaLocation="http://www.openarchives.org/OAI/2.0/oai_dc/ http://www.openarchives.org/OAI/2.0/oai_dc.xsd">
  <dc:creators>Dia!kwain (David Hoesar) (V)</dc:creators>
  <dc:date>2020-09-12</dc:date>
  <dc:description>He changes himself into a jackal, and goes to find out what is detaining his people, when they do not return home. In the Katkop dialect, by Dia!kwain (L V.-19. 5506 rev.-5512 rev.). Sorcerers' hearts become stars and come out of the sky when they die. In the form of a jackal, sorcerers seek people from their homes at night to see where they are and how they are doing. 1) See also About sorcerers: their death, their snoring work, earthquakes and the rain and !nuin-|kui-ten (who was a sorcerer or magician), 2) This story is found in Book V-19.</dc:description>
  <dc:format>Unqualified Dublin Core</dc:format>
  <dc:identifier>http://pumbaa.cs.uct.ac.za/~balnew/metadata/stories/494</dc:identifier>
  <dc:publisher>Lucy Lloyd</dc:publisher>
  <dc:rights>CC-BY-NC-ND</dc:rights>
  <dc:source>Lucy Lloyd</dc:source>
  <dc:subject>Lucy Lloyd |xam notebooks</dc:subject>
  <dc:title>More about sorcerers</dc:title>
  <dc:type>story</dc:type>
</oai_dc:dc>
