<?xml version='1.0' encoding='utf-8'?>
<oai_dc:dc xmlns:dc="http://purl.org/dc/elements/1.1/" xmlns:oai_dc="http://www.openarchives.org/OAI/2.0/oai_dc/" xmlns:xsi="http://www.w3.org/2001/XMLSchema-instance" xsi:schemaLocation="http://www.openarchives.org/OAI/2.0/oai_dc/ http://www.openarchives.org/OAI/2.0/oai_dc.xsd">
  <dc:description>A man, who has missed his aim in shooting, throws springbok bones, in order that another man may do likewise. (L VIII.</dc:description>
  <dc:description>11. 7010 rev., note). !hau</dc:description>
  <dc:description>!hau is a charm made so that a man may make another miss his aim on the hunting</dc:description>
  <dc:description>ground.</dc:description>
  <dc:identifier>http://pumbaa.cs.uct.ac.za/~balnew/metadata/stories/674</dc:identifier>
  <dc:title>!hau</dc:title>
  <dc:title>!hau Explanation of  (a hunting charm)</dc:title>
</oai_dc:dc>
