<item type="story"><id>464</id>
<collection>Lucy Lloyd |xam notebooks</collection>
<title>A prayer addressed to the Moon, and another version of the Moon and Hare story</title>
<summary><i>A version of the Moon and Hare story (which treats of the Origin of Death), preceded by a prayer, addressed to the young Moon. In the Katkop dialect, by Díä!kwãin (L V.-15. 5159-5168 1/2, 16. 5169-5198). </i>A prayer to the new Moon and an account of the origin of death.</summary><comments>1) pp.5173-5260 were translated in April 1912; except for pp.5206-5209, 2) Date on p.5169: 6 August, 3) p. 5172v: a note added 7 October 1875 (translated in April 1912), 3) p.5178v: a piece of &apos;biltong&apos; flesh is removed from inside the Hare&apos;s flesh by hunters when they kill it, 4) See also <i>The Moon and the Hare</i> and the other &apos;Moon and Hare&apos; stories, 5) This story is found in Books V-15 and V-16</comments><date>August 1875</date><storypages>5159-5168 1/2, 5169-5198</storypages><category>Celestial bodies and aeroscopy</category><author>Dia!kwain (David Hoesar) (V)</author><keyword><kw>Moon</kw><subkw>a prayer addressed to</subkw></keyword>
<keyword><kw>Moon</kw><subkw>and Moon and Hare story</subkw></keyword>
<keyword><kw>Moon</kw><subkw>and the origin of death</subkw></keyword>
<keyword><kw>Moon</kw><subkw>curses the Hare</subkw></keyword>
<keyword><kw>Moon</kw><subkw>his fight with the Hare</subkw></keyword>
<keyword><kw>Moon</kw><subkw>tells people they will live again</subkw></keyword>
<keyword><kw>Moon</kw><subkw>the people&apos;s prayer to</subkw></keyword>
<keyword><kw>Moon</kw><subkw>the resurrection of</subkw></keyword>
<keyword><kw>Moon</kw><subkw>&apos;living returns&apos;</subkw></keyword>
<keyword><kw>Moon</kw><subkw>waxes and wanes</subkw></keyword>
<keyword><kw>Moon</kw><subkw>and death</subkw></keyword>
<keyword><kw>Moon</kw><subkw>does not die</subkw></keyword>
<keyword><kw>Moon</kw><subkw>and the Hare</subkw></keyword>
<keyword><kw>Moon</kw><subkw>prayer to the new</subkw></keyword>
<keyword><kw>Moon</kw><subkw>prayer to the young</subkw></keyword>
<keyword><kw>Moon</kw><subkw>actions performed during prayers to</subkw></keyword>
<keyword><kw>Moon</kw><subkw>the people wish to resemble it and live again</subkw></keyword>
<keyword><kw>Hare</kw><subkw>and a prayer addressed to the Moon</subkw></keyword>
<keyword><kw>Hare</kw><subkw>and Moon and Hare story</subkw></keyword>
<keyword><kw>Hare</kw><subkw>shakes his head</subkw></keyword>
<keyword><kw>Hare</kw><subkw>lice inhabit his head</subkw></keyword>
<keyword><kw>Hare</kw><subkw>is cursed by the Moon</subkw></keyword>
<keyword><kw>Hare</kw><subkw>where hares live</subkw></keyword>
<keyword><kw>Hare</kw><subkw>hares are eaten by beasts of prey</subkw></keyword>
<keyword><kw>Hare</kw><subkw>did not &apos;assent&apos; to the Moon</subkw></keyword>
<keyword><kw>Hare</kw><subkw>and the origin of death</subkw></keyword>
<keyword><kw>Hare</kw><subkw>hare-meat gives people heartburn</subkw></keyword>
<keyword><kw>Hare</kw><subkw>avoidance of eating hare-meat</subkw></keyword>
<keyword><kw>Hare</kw><subkw>hare-meat contains a piece of human flesh</subkw></keyword>
<keyword><kw>Hare</kw><subkw>was formerly a person</subkw></keyword>
<keyword><kw>Hare</kw><subkw>became a Hare</subkw></keyword>
<keyword><kw>Hare</kw><subkw>and the Moon&apos;s speech</subkw></keyword>
<keyword><kw>Hare</kw><subkw>and death</subkw></keyword>
<keyword><kw>Hare</kw><subkw>and resurrection</subkw></keyword>
<keyword><kw>Hare</kw><subkw>the death of his mother</subkw></keyword>
<keyword><kw>Hare</kw><subkw>contradicts the Moon</subkw></keyword>
<keyword><kw>Hare</kw><subkw>his fight with the Moon</subkw></keyword>
<keyword><kw>Hare</kw><subkw>his mouth is struck by the angry Moon</subkw></keyword>
<keyword><kw>Hare</kw><subkw>accounting for the appearance of the Hare</subkw></keyword>
<keyword><kw>Hare</kw><subkw>his speech to people about death</subkw></keyword>
<keyword><kw>Hare</kw><subkw>his mouth-scar</subkw></keyword>
<keyword><kw>Hare</kw><subkw>the Moon&apos;s curse and the nature and habits of hares</subkw></keyword>
<keyword><kw>Hare</kw><subkw>will die</subkw></keyword>
<keyword><kw>death</kw><subkw>and a prayer addressed to the Moon</subkw></keyword>
<keyword><kw>death</kw><subkw>and Moon and Hare story</subkw></keyword>
<keyword><kw>death</kw><subkw>and the Moon&apos;s curse</subkw></keyword>
<keyword><kw>death</kw><subkw>the origin of</subkw></keyword>
<keyword><kw>death</kw><subkw>the creation of</subkw></keyword>
<keyword><kw>death</kw><subkw>people &apos;altogether die&apos;</subkw></keyword>
<keyword><kw>death</kw><subkw>of the Hare&apos;s mother</subkw></keyword>
<keyword><kw>death</kw><subkw>the Moon and the Hare&apos;s speeches about</subkw></keyword>
<keyword><kw>death</kw><subkw>and resurrection</subkw></keyword>
<keyword><kw>death</kw><subkw>and how people were once reborn, like the Moon</subkw></keyword>
<keyword><kw>fight</kw><subkw>between the Moon and the Hare</subkw></keyword>
<keyword><kw>speech</kw><subkw>the Moon&apos;s to people about death</subkw></keyword>
<keyword><kw>speech</kw><subkw>and Moon and Hare story</subkw></keyword>
<keyword><kw>origin</kw><subkw>of death</subkw></keyword>
<keyword><kw>origin</kw><subkw>and Moon and Hare story</subkw></keyword>
<keyword><kw>resurrection</kw><subkw>and Moon and Hare story</subkw></keyword>
<keyword><kw>resurrection</kw><subkw>and a prayer addressed to the Moon</subkw></keyword>
<keyword><kw>resurrection</kw><subkw>of the Moon who lives again</subkw></keyword>
<keyword><kw>resurrection</kw><subkw>and the origins of death</subkw></keyword>
<keyword><kw>resurrection</kw><subkw>how people were once reborn, like the Moon</subkw></keyword>
<keyword><kw>resurrection</kw><subkw>the people wish to resemble the Moon and live again</subkw></keyword>
<keyword><kw>origin</kw><subkw>of death</subkw></keyword>
<keyword><kw>origin</kw><subkw>and Moon and Hare story</subkw></keyword>
<keyword><kw>curse</kw><subkw>by the Moon of the Hare</subkw></keyword>
<keyword><kw>curse</kw><subkw>accounting for the habits and appearance of hares</subkw></keyword>
<keyword><kw>curse</kw><subkw>and Moon and Hare story</subkw></keyword>
<keyword><kw>animals</kw><subkw>accounting for the habits and appearance of hares</subkw></keyword>
<keyword><kw>animals</kw><subkw>the origin of the hare&apos;s &apos;mouth-scar&apos; or hare-lip</subkw></keyword>
<keyword><kw>animals</kw><subkw>and Moon and Hare story</subkw></keyword>
<keyword><kw>food</kw><subkw>eating hare-meat</subkw></keyword>
<keyword><kw>food</kw><subkw>avoidance of eating hare-meat</subkw></keyword>
<keyword><kw>food</kw><subkw>and Moon and Hare story</subkw></keyword>
<keyword><kw>flesh</kw><subkw>hare-meat contains a piece of human flesh</subkw></keyword>
<keyword><kw>flesh</kw><subkw>and Moon and Hare story</subkw></keyword>
<keyword><kw>address</kw><subkw>a prayer addressed to the Moon</subkw></keyword>
<keyword><kw>address</kw><subkw>and Moon and Hare story</subkw></keyword>
<keyword><kw>address</kw><subkw>actions performed during</subkw></keyword>

<page><file>A2_1_64_05159.JPG</file><book>BC_151_A2_1_064</book></page>
<page><file>A2_1_64_05160.JPG</file><book>BC_151_A2_1_064</book></page>
<page><file>A2_1_64_05161.JPG</file><book>BC_151_A2_1_064</book></page>
<page><file>A2_1_64_05162.JPG</file><book>BC_151_A2_1_064</book></page>
<page><file>A2_1_64_05163.JPG</file><book>BC_151_A2_1_064</book></page>
<page><file>A2_1_64_05164.JPG</file><book>BC_151_A2_1_064</book></page>
<page><file>A2_1_64_05165.JPG</file><book>BC_151_A2_1_064</book></page>
<page><file>A2_1_64_05166.JPG</file><book>BC_151_A2_1_064</book></page>
<page><file>A2_1_64_05167.JPG</file><book>BC_151_A2_1_064</book></page>
<page><file>A2_1_64_051681_2.JPG</file><book>BC_151_A2_1_064</book></page>
<page><file>A2_1_65_05169.JPG</file><book>BC_151_A2_1_065</book></page>
<page><file>A2_1_65_05170.JPG</file><book>BC_151_A2_1_065</book></page>
<page><file>A2_1_65_05171.JPG</file><book>BC_151_A2_1_065</book></page>
<page><file>A2_1_65_05172.JPG</file><book>BC_151_A2_1_065</book></page>
<page><file>A2_1_65_05173.JPG</file><book>BC_151_A2_1_065</book></page>
<page><file>A2_1_65_05174.JPG</file><book>BC_151_A2_1_065</book></page>
<page><file>A2_1_65_05175.JPG</file><book>BC_151_A2_1_065</book></page>
<page><file>A2_1_65_05176.JPG</file><book>BC_151_A2_1_065</book></page>
<page><file>A2_1_65_05177.JPG</file><book>BC_151_A2_1_065</book></page>
<page><file>A2_1_65_05178.JPG</file><book>BC_151_A2_1_065</book></page>
<page><file>A2_1_65_05179.JPG</file><book>BC_151_A2_1_065</book></page>
<page><file>A2_1_65_05180.JPG</file><book>BC_151_A2_1_065</book></page>
<page><file>A2_1_65_05181.JPG</file><book>BC_151_A2_1_065</book></page>
<page><file>A2_1_65_05182.JPG</file><book>BC_151_A2_1_065</book></page>
<page><file>A2_1_65_05183.JPG</file><book>BC_151_A2_1_065</book></page>
<page><file>A2_1_65_05184.JPG</file><book>BC_151_A2_1_065</book></page>
<page><file>A2_1_65_05185.JPG</file><book>BC_151_A2_1_065</book></page>
<page><file>A2_1_65_05186.JPG</file><book>BC_151_A2_1_065</book></page>
<page><file>A2_1_65_05187.JPG</file><book>BC_151_A2_1_065</book></page>
<page><file>A2_1_65_05188.JPG</file><book>BC_151_A2_1_065</book></page>
<page><file>A2_1_65_05189.JPG</file><book>BC_151_A2_1_065</book></page>
<page><file>A2_1_65_05190.JPG</file><book>BC_151_A2_1_065</book></page>
<page><file>A2_1_65_05191.JPG</file><book>BC_151_A2_1_065</book></page>
<page><file>A2_1_65_05192.JPG</file><book>BC_151_A2_1_065</book></page>
<page><file>A2_1_65_05193.JPG</file><book>BC_151_A2_1_065</book></page>
<page><file>A2_1_65_05194.JPG</file><book>BC_151_A2_1_065</book></page>
<page><file>A2_1_65_05195.JPG</file><book>BC_151_A2_1_065</book></page>
<page><file>A2_1_65_05196.JPG</file><book>BC_151_A2_1_065</book></page>
<page><file>A2_1_65_05197.JPG</file><book>BC_151_A2_1_065</book></page>
<page><file>A2_1_65_05198.JPG</file><book>BC_151_A2_1_065</book></page>
</item>
