<?xml version='1.0' encoding='utf-8'?>
<oai_dc:dc xmlns:dc="http://purl.org/dc/elements/1.1/" xmlns:oai_dc="http://www.openarchives.org/OAI/2.0/oai_dc/" xmlns:xsi="http://www.w3.org/2001/XMLSchema-instance" xsi:schemaLocation="http://www.openarchives.org/OAI/2.0/oai_dc/ http://www.openarchives.org/OAI/2.0/oai_dc.xsd">
  <dc:creator>|han=kass'o (Klein Jantje) (VIII)</dc:creator>
  <dc:date>2020-09-14</dc:date>
  <dc:description>||xuobbeten is carried away by the lion while she sleeps. It bites her head and kills her. It puts her in its mouth and carries her down to the water. The people name the water '||xuobbeten' because it has no bushes. 1) p.7217v: |han=kass'o heard this story from his father-in-law (||kabbo), 2) p.7219v: see The !kwana thorn tree, 3) See p.7215v for further details about ||xuobbeten, 4) This story is found in Book VIII-14.</dc:description>
  <dc:format>Unqualified Dublin Core</dc:format>
  <dc:identifier>http://pumbaa.cs.uct.ac.za/~balnew/metadata/stories/700</dc:identifier>
  <dc:publisher>Lucy Lloyd</dc:publisher>
  <dc:rights>CC-BY-NC-ND</dc:rights>
  <dc:source>Lucy Lloyd</dc:source>
  <dc:subject>Lucy Lloyd |xam notebooks</dc:subject>
  <dc:title>||xuobbeten and the lion</dc:title>
  <dc:type>story</dc:type>
</oai_dc:dc>
