<?xml version='1.0' encoding='utf-8'?>
<oai_dc:dc xmlns:dc="http://purl.org/dc/elements/1.1/" xmlns:oai_dc="http://www.openarchives.org/OAI/2.0/oai_dc/" xmlns:xsi="http://www.w3.org/2001/XMLSchema-instance" xsi:schemaLocation="http://www.openarchives.org/OAI/2.0/oai_dc/ http://www.openarchives.org/OAI/2.0/oai_dc.xsd">
  <dc:description>Sh </dc:description>
  <dc:description>|  , a Bushman vegetable medicine, used also as a charm (L II.</dc:description>
  <dc:description>36. 3242</dc:description>
  <dc:description>3261). How one man fights with another, having previously rubbed his own hands with Sh </dc:description>
  <dc:description>|  ; and how he afterwards restores the man with whom he fought, by means of a fresh application of Sh </dc:description>
  <dc:description>|   (L II.</dc:description>
  <dc:description>36. 3262</dc:description>
  <dc:description>3268). ,</dc:description>
  <dc:identifier>309</dc:identifier>
  <dc:title>Ssho |oa or ||karruken</dc:title>
  <dc:title>||karruken or |u ssho a</dc:title>
</oai_dc:dc>
