<?xml version='1.0' encoding='utf-8'?>
<oai_dc:dc xmlns:dc="http://purl.org/dc/elements/1.1/" xmlns:oai_dc="http://www.openarchives.org/OAI/2.0/oai_dc/" xmlns:xsi="http://www.w3.org/2001/XMLSchema-instance" xsi:schemaLocation="http://www.openarchives.org/OAI/2.0/oai_dc/ http://www.openarchives.org/OAI/2.0/oai_dc.xsd">
  <dc:descriptions>Information regarding narrator’s family. In English after and in Bushman by /han≠kass’o (L VIII.-1. 6052 and 6053, 19. 7671, 26. 8302 rev.).</dc:descriptions>
  <dc:descriptions>Information about the younger brother of |han≠kass'o's grandfather Tsatsi, called !xein (or Dirk).</dc:descriptions>
  <dc:identifiers>774</dc:identifiers>
  <dc:title>Dirk (!xein, son of Dootje)</dc:title>
</oai_dc:dc>
