<?xml version='1.0' encoding='utf-8'?>
<oai_dc:dc xmlns:dc="http://purl.org/dc/elements/1.1/" xmlns:oai_dc="http://www.openarchives.org/OAI/2.0/oai_dc/" xmlns:xsi="http://www.w3.org/2001/XMLSchema-instance" xsi:schemaLocation="http://www.openarchives.org/OAI/2.0/oai_dc/ http://www.openarchives.org/OAI/2.0/oai_dc.xsd">
  <dc:descriptions>Further details concerning what occurs at the death of a sorcerer, and concerning the harmful and beneficial doings of sorcerers (L V.</dc:descriptions>
  <dc:descriptions>19. 5506</dc:descriptions>
  <dc:descriptions>5530). When a sorcerer dies, an earthquake takes place, and a star shoots. Even when asleep, a sorcerer knows what is going about in the night; and takes care of the people, defending them from the sorcerers. (L V.</dc:descriptions>
  <dc:descriptions>19. 5531</dc:descriptions>
  <dc:descriptions>5536 1/2). Sorcerers' hearts sound like the rain when they die and their hearts fall into waterpits. Parents say they fear falling stars, because they know things that happen and always fall for a reason. Sorcerers can send their sorcery to different places to 'spirit' people away or kill them.</dc:descriptions>
  <dc:identifiers>493</dc:identifiers>
  <dc:title>About sorcerers: their death, their snoring work, earthquakes and the rain</dc:title>
</oai_dc:dc>
