<item type="story"><id>37</id>
<collection>Wilhelm Bleek notebooks</collection>
<title>|kaggen (the Mantis) and the Moon (version 1)</title>
<summary>The origin of the Moon is an episode in the story of the Mantis and his pet eland. When the Suricats, who were present at the cutting up of the eland, ill-treaded the mantis, he found upon a bush another eland’s gall-bladder, and this (as mentioned above) he pierced and broke, thereby creating a darkness into which he sprang; but, being inconvenienced by it, he took off one of his shoes and threw it into the sky, with the order that it should become the moon. Thus the moon is red, because the shoe of the Mantis was covered with the red dust of the Bushmanland, and cold, because it is only leather. We have two versions of this myth, a shorter one (LII.-24. 482-486), and a longer one, in which a good deal of conversation is introduced (BII. 379-390, 421-428, III.429-433), of which the final speech of the Mantis, as treating of the reasons for the changes of the moon, is referred to the latter heading. Whilst in the preceding myths of the Mantis, the Moon, according to its origin, is only a piece of leather (a shoe of the Mantis),–in Bushman astrological mythology the Moon is looked upon as a man who incurs the wrath of the Sun, and is consequently pierced by the knife (i.e. rays) of the latter.  This process is repeated until almost the whole of the Moon is cut away, and only one little piece left; which the Moon piteously implores the Sun to spare for his (the Moon’s) children.  (As mentioned above, the Moon is in Bushman mythology a male being.)  From this little piece, the Moon gradually grows again until it becomes a full moon, when the Sun’s stabbing and cutting processes recommence.– This explanation of the Moon’s changes is given in four versions;  the longest of which (although as yet unfinished) is in a speech made by the Mantis, when he had created the Moon.  BIII. 434–437, 432a–437a, 438–460, 501–514, IV. 515–526, 528–584, V. 585–590, XVL. 1497–1590, XVII. 1591–1683, XVIII 1698–1711, 1725–1758) <i>|kaggen fights with the Meerkats and pierces the gall of the dead eland (which was formerly |kaggen&apos;s pet). |kaggen creates the Moon from his veldskoen, which he throws into the sky to light the darkness. The story continues about the Moon and how it is stabbed by the Sun. The angry Sun follows the spoor of the Moon as it (the Moon) travels in the sky. The Sun intends to fight the Moon. The Moon is pierced by the knife or rays of the Sun. In pain, the Moon sets slowly and dies but is reborn the next night when it lights up the darkness. A part of the Moon remains in the sky and lives while its decayed and wounded part dies away. The part of the Moon that lives is joined to its head, its face and its thinking strings. As the Moon grows, so does its stomach which becomes full and gives light for the people on the ground.</i></summary><comments>1) p.422v: A note on the throat arteries, which house the thinking strings and are the instruments of thought, 2) p.547v: names of groups of |xam: Flat and Hartebeest River |xam, the <i>|ka</i> people, and the <i>!khouga !ko</i> [illegible] people; the names of trees (thorn), 3) p.576v: &apos;body&apos; parts of the Moon (shoulder-flesh and neckhole), 4) Date on p.1496v: 21 March 1873 (notes added), 5) Date on p.1515v: March 1920 &apos;DB&apos; or Dorothea Bleek, 6) Insert found between pp.1549-1550 featuring |xam vocabulary, 7) This story is found in Books II-V and XVI-XVIII</comments><date>1871, 1872, March 1873 (notes added)</date><storypages>379-390, 421-428, 429-460, 501-514, 515-526, 528-590, 1497-1590, 1591-1683, 1698-1711, 1725-1758</storypages><category>|kaggen (the Mantis)</category><category>Celestial bodies and aeroscopy</category><author>||kabbo (Jantje) (II)</author><keyword><kw>Sun</kw><subkw>|kaggen and the Moon and</subkw></keyword>
<keyword><kw>Sun</kw><subkw>follows the Moon&apos;s spoor</subkw></keyword>
<keyword><kw>Sun</kw><subkw>rises and sets</subkw></keyword>
<keyword><kw>Sun</kw><subkw>and the death of the Moon</subkw></keyword>
<keyword><kw>Sun</kw><subkw>and the creation of the Moon</subkw></keyword>
<keyword><kw>Sun</kw><subkw>about</subkw></keyword>
<keyword><kw>Sun</kw><subkw>doings of</subkw></keyword>
<keyword><kw>Sun</kw><subkw>armpit of</subkw></keyword>
<keyword><kw>Sun</kw><subkw>armhole of</subkw></keyword>
<keyword><kw>Sun</kw><subkw>weapons of</subkw></keyword>
<keyword><kw>Sun</kw><subkw>assegai of</subkw></keyword>
<keyword><kw>Sun</kw><subkw>knife of</subkw></keyword>
<keyword><kw>Sun</kw><subkw>rays of</subkw></keyword>
<keyword><kw>Sun</kw><subkw>house of</subkw></keyword>
<keyword><kw>Sun</kw><subkw>spear of</subkw></keyword>
<keyword><kw>Sun</kw><subkw>stabs</subkw></keyword>
<keyword><kw>Sun</kw><subkw>cuts the Moon&apos;s side</subkw></keyword>
<keyword><kw>Sun</kw><subkw>is angry</subkw></keyword>
<keyword><kw>Sun</kw><subkw>pierces the Moon</subkw></keyword>
<keyword><kw>Moon</kw><subkw>|kaggen and the Moon</subkw></keyword>
<keyword><kw>Moon</kw><subkw>body parts of</subkw></keyword>
<keyword><kw>Moon</kw><subkw>what the people say about</subkw></keyword>
<keyword><kw>Moon</kw><subkw>and the |xam</subkw></keyword>
<keyword><kw>Moon</kw><subkw>&apos;running meets the clouds&apos;</subkw></keyword>
<keyword><kw>Moon</kw><subkw>lights the ground</subkw></keyword>
<keyword><kw>Moon</kw><subkw>&apos;stands&apos;</subkw></keyword>
<keyword><kw>Moon</kw><subkw>footpath of</subkw></keyword>
<keyword><kw>Moon</kw><subkw>talks</subkw></keyword>
<keyword><kw>Moon</kw><subkw>parts of</subkw></keyword>
<keyword><kw>Moon</kw><subkw>father of</subkw></keyword>
<keyword><kw>Moon</kw><subkw>children of</subkw></keyword>
<keyword><kw>Moon</kw><subkw>size of</subkw></keyword>
<keyword><kw>Moon</kw><subkw>waxes and wanes</subkw></keyword>
<keyword><kw>Moon</kw><subkw>wound of</subkw></keyword>
<keyword><kw>Moon</kw><subkw>lives and dies</subkw></keyword>
<keyword><kw>Moon</kw><subkw>resurrection of</subkw></keyword>
<keyword><kw>Moon</kw><subkw>death of</subkw></keyword>
<keyword><kw>Moon</kw><subkw>|kaggen makes</subkw></keyword>
<keyword><kw>Moon</kw><subkw>and the Meerkats</subkw></keyword>
<keyword><kw>Moon</kw><subkw>and the eland&apos;s gall</subkw></keyword>
<keyword><kw>Moon</kw><subkw>doings of</subkw></keyword>
<keyword><kw>Moon</kw><subkw>colour of</subkw></keyword>
<keyword><kw>Moon</kw><subkw>appearance of</subkw></keyword>
<keyword><kw>Moon</kw><subkw>&apos;the devil&apos;s veldschoen&apos;</subkw></keyword>
<keyword><kw>Moon</kw><subkw>&apos;thinking strings&apos; of</subkw></keyword>
<keyword><kw>Moon</kw><subkw>is pierced</subkw></keyword>
<keyword><kw>Moon</kw><subkw>is cut</subkw></keyword>
<keyword><kw>Moon</kw><subkw>light of</subkw></keyword>
<keyword><kw>Moon</kw><subkw>shines</subkw></keyword>
<keyword><kw>Moon</kw><subkw>sets</subkw></keyword>
<keyword><kw>Moon</kw><subkw>little</subkw></keyword>
<keyword><kw>Moon</kw><subkw>cool</subkw></keyword>
<keyword><kw>Moon</kw><subkw>side of</subkw></keyword>
<keyword><kw>Moon</kw><subkw>relations of</subkw></keyword>
<keyword><kw>Moon</kw><subkw>wife of</subkw></keyword>
<keyword><kw>Moon</kw><subkw>backbone of</subkw></keyword>
<keyword><kw>Moon</kw><subkw>red</subkw></keyword>
<keyword><kw>Moon</kw><subkw>&apos;great one&apos;</subkw></keyword>
<keyword><kw>Moon</kw><subkw>&apos;softly goes&apos;</subkw></keyword>
<keyword><kw>Moon</kw><subkw>&apos;gently goes&apos;</subkw></keyword>
<keyword><kw>Moon</kw><subkw>house of</subkw></keyword>
<keyword><kw>Moon</kw><subkw>children are clever and &apos;understand&apos;</subkw></keyword>
<keyword><kw>Moon</kw><subkw>pain of</subkw></keyword>
<keyword><kw>Moon</kw><subkw>head of</subkw></keyword>
<keyword><kw>Moon</kw><subkw>flesh smells badly</subkw></keyword>
<keyword><kw>Moon</kw><subkw>round</subkw></keyword>
<keyword><kw>Moon</kw><subkw>new</subkw></keyword>
<keyword><kw>Moon</kw><subkw>old</subkw></keyword>
<keyword><kw>Moon</kw><subkw>full</subkw></keyword>
<keyword><kw>Moon</kw><subkw>three-quarter</subkw></keyword>
<keyword><kw>Moon</kw><subkw>like fire</subkw></keyword>
<keyword><kw>Moon</kw><subkw>grown-up</subkw></keyword>
<keyword><kw>Moon</kw><subkw>belly of</subkw></keyword>
<keyword><kw>Moon</kw><subkw>neck of</subkw></keyword>
<keyword><kw>Moon</kw><subkw>vertebra of</subkw></keyword>
<keyword><kw>Moon</kw><subkw>&apos;puikwax&apos; of</subkw></keyword>
<keyword><kw>Moon</kw><subkw>&apos;paxwax&apos; of</subkw></keyword>
<keyword><kw>Moon</kw><subkw>spoor of</subkw></keyword>
<keyword><kw>Moon</kw><subkw>grows</subkw></keyword>
<keyword><kw>Moon</kw><subkw>stomach of</subkw></keyword>
<keyword><kw>Moon</kw><subkw>hunger of</subkw></keyword>
<keyword><kw>Moon</kw><subkw>scarred</subkw></keyword>
<keyword><kw>Moon</kw><subkw>shoulder top of</subkw></keyword>
<keyword><kw>Moon</kw><subkw>shoulder blade of</subkw></keyword>
<keyword><kw>Moon</kw><subkw>&apos;returning comes&apos;</subkw></keyword>
<keyword><kw>Moon</kw><subkw>tooth of</subkw></keyword>
<keyword><kw>Moon</kw><subkw>&apos;ill stands&apos;</subkw></keyword>
<keyword><kw>Moon</kw><subkw>time of</subkw></keyword>
<keyword><kw>Moon</kw><subkw>blood of</subkw></keyword>
<keyword><kw>Moon</kw><subkw>skin of burns</subkw></keyword>
<keyword><kw>Moon</kw><subkw>lies in sky</subkw></keyword>
<keyword><kw>Moon</kw><subkw>&apos;putrid flesh&apos; of</subkw></keyword>
<keyword><kw>Moon</kw><subkw>&apos;decayed flesh&apos; of</subkw></keyword>
<keyword><kw>Moon</kw><subkw>and darkness</subkw></keyword>
<keyword><kw>Moon</kw><subkw>and night</subkw></keyword>
<keyword><kw>Moon</kw><subkw>fresh</subkw></keyword>
<keyword><kw>Moon</kw><subkw>vigorous</subkw></keyword>
<keyword><kw>Moon</kw><subkw>young</subkw></keyword>
<keyword><kw>Moon</kw><subkw>creation of the</subkw></keyword>
<keyword><kw>Moon</kw><subkw>eland&apos;s gall and</subkw></keyword>
<keyword><kw>Moon</kw><subkw>is |kaggen&apos;s veldskoen or shoe</subkw></keyword>
<keyword><kw>heavens</kw><subkw>|kaggen and the Moon and</subkw></keyword>
<keyword><kw>heavens</kw><subkw>things of</subkw></keyword>
<keyword><kw>heavens</kw><subkw>and the Moon</subkw></keyword>
<keyword><kw>heavens</kw><subkw>and the Sun</subkw></keyword>
<keyword><kw>heavens</kw><subkw>creation of the Moon in</subkw></keyword>
<keyword><kw>paxwax</kw><subkw>&apos;puikwax&apos;</subkw></keyword>
<keyword><kw>paxwax</kw><subkw>|kaggen and the Moon and</subkw></keyword>
<keyword><kw>paxwax</kw><subkw>the Moon&apos;s</subkw></keyword>
<keyword><kw>paxwax</kw><subkw>&apos;panwax&apos;</subkw></keyword>
<keyword><kw>paxwax</kw><subkw>creation of the Moon and</subkw></keyword>
<keyword><kw>thinking strings</kw><subkw>|kaggen and the Moon and</subkw></keyword>
<keyword><kw>thinking strings</kw><subkw>the Moon&apos;s</subkw></keyword>
<keyword><kw>thinking strings</kw><subkw>of |xam</subkw></keyword>
<keyword><kw>thinking strings</kw><subkw>the location of</subkw></keyword>
<keyword><kw>thinking strings</kw><subkw>in the throat arteries</subkw></keyword>
<keyword><kw>thinking strings</kw><subkw>are instruments of thought</subkw></keyword>
<keyword><kw>|kaggen</kw><subkw>the Mantis</subkw></keyword>
<keyword><kw>|kaggen</kw><subkw>and the Moon and</subkw></keyword>
<keyword><kw>|kaggen</kw><subkw>creates the Moon</subkw></keyword>
<keyword><kw>|kaggen</kw><subkw>his things</subkw></keyword>
<keyword><kw>|kaggen</kw><subkw>fights with the Meerkats</subkw></keyword>
<keyword><kw>|kaggen</kw><subkw>makes fire</subkw></keyword>
<keyword><kw>|kaggen</kw><subkw>is a &apos;rogue&apos;</subkw></keyword>
<keyword><kw>|kaggen</kw><subkw>doings of</subkw></keyword>
<keyword><kw>|kaggen</kw><subkw>actions of</subkw></keyword>
<keyword><kw>|kaggen</kw><subkw>springs into darkness</subkw></keyword>
<keyword><kw>|kaggen</kw><subkw>is a &apos;devil&apos;</subkw></keyword>
<keyword><kw>|kaggen</kw><subkw>and the eland&apos;s gall</subkw></keyword>
<keyword><kw>|kaggen</kw><subkw>and the Meerkats</subkw></keyword>
<keyword><kw>|kaggen</kw><subkw>shoe or veldskoen of</subkw></keyword>
<keyword><kw>Meerkats</kw><subkw>|kaggen and the Moon and</subkw></keyword>
<keyword><kw>Meerkats</kw><subkw>fight with |kaggen</subkw></keyword>
<keyword><kw>Meerkats</kw><subkw>killed the eland</subkw></keyword>
<keyword><kw>Meerkats</kw><subkw>creation of the Moon and</subkw></keyword>
<keyword><kw>eland&apos;s gall</kw><subkw>in the tree</subkw></keyword>
<keyword><kw>eland&apos;s gall</kw><subkw>|kaggen and the Moon and</subkw></keyword>
<keyword><kw>eland&apos;s gall</kw><subkw>creation of the Moon with</subkw></keyword>
<keyword><kw>eland&apos;s gall</kw><subkw>is thrown into the sky</subkw></keyword>
<keyword><kw>eland&apos;s gall</kw><subkw>is pierced by |kaggen and breaks</subkw></keyword>
<keyword><kw>Bushmanland</kw><subkw>the ground is red in</subkw></keyword>
<keyword><kw>Ichneumon</kw><subkw>|kaggen and the Moon and</subkw></keyword>
<keyword><kw>Ichneumon</kw><subkw>creation of the Moon and</subkw></keyword>
<keyword><kw>death</kw><subkw>of the Moon</subkw></keyword>
<keyword><kw>death</kw><subkw>|kaggen and the Moon and</subkw></keyword>
<keyword><kw>|xam</kw><subkw>groups of</subkw></keyword>
<keyword><kw>|xam</kw><subkw>&apos;Bushman tribes&apos;</subkw></keyword>
<keyword><kw>|xam</kw><subkw>names of groups</subkw></keyword>
<keyword><kw>child</kw><subkw>Moon&apos;s</subkw></keyword>
<keyword><kw>child</kw><subkw>|kaggen and the Moon and</subkw></keyword>
<keyword><kw>eland</kw><subkw>its gall</subkw></keyword>
<keyword><kw>eland</kw><subkw>|kaggen and the Moon and</subkw></keyword>
<keyword><kw>creation</kw><subkw>of the Moon</subkw></keyword>
<keyword><kw>creation</kw><subkw>|kaggen and the Moon and</subkw></keyword>
<keyword><kw>fight</kw><subkw>|kaggen and the Moon and</subkw></keyword>
<keyword><kw>fight</kw><subkw>of the Meerkats and |kaggen</subkw></keyword>
<keyword><kw>names</kw><subkw>of groups of |xam</subkw></keyword>
<keyword><kw>names</kw><subkw>of &apos;Bushman tribes&apos;</subkw></keyword>
<keyword><kw>names</kw><subkw>|kaggen and the Moon</subkw></keyword>
<keyword><kw>spoor</kw><subkw>of the Moon</subkw></keyword>
<keyword><kw>spoor</kw><subkw>|kaggen and the Moon</subkw></keyword>
<keyword><kw>armpit</kw><subkw>Sun&apos;s</subkw></keyword>
<keyword><kw>armpit</kw><subkw>|kaggen and the Moon</subkw></keyword>
<keyword><kw>vertebra</kw><subkw>the Moon&apos;s</subkw></keyword>
<keyword><kw>vertebra</kw><subkw>|kaggen and the Moon</subkw></keyword>
<keyword><kw>knife</kw><subkw>used by the Sun to pierce the Moon</subkw></keyword>
<keyword><kw>knife</kw><subkw>|kaggen and the Moon</subkw></keyword>
<keyword><kw>weapons</kw><subkw>of the Sun</subkw></keyword>
<keyword><kw>weapons</kw><subkw>|kaggen and the Moon</subkw></keyword>
<keyword><kw>weapons</kw><subkw>Sun&apos;s assegai, knife, spear</subkw></keyword>
<keyword><kw>house</kw><subkw>the Sun&apos;s</subkw></keyword>
<keyword><kw>house</kw><subkw>|kaggen and the Moon</subkw></keyword>
<keyword><kw>shoe</kw><subkw>|kaggen&apos;s veldskoen</subkw></keyword>
<keyword><kw>shoe</kw><subkw>|kaggen and the Moon</subkw></keyword>
<keyword><kw>things</kw><subkw>|kaggen&apos;s</subkw></keyword>
<keyword><kw>things</kw><subkw>|kaggen and the Moon</subkw></keyword>
<keyword><kw>speech</kw><subkw>of the Moon who talks</subkw></keyword>
<keyword><kw>speech</kw><subkw>|kaggen and the Moon</subkw></keyword>
<keyword><kw>veldskoen</kw><subkw>the devil’s ‘veldschoen’</subkw></keyword>
<keyword><kw>veldskoen</kw><subkw>|kaggen’s shoe</subkw></keyword>
<keyword><kw>veldskoen</kw><subkw>|kaggen and the Moon</subkw></keyword>

<page><file>A1_4_2_00379.JPG</file><book>BC_151_A1_4_002</book></page>
<page><file>A1_4_2_00380.JPG</file><book>BC_151_A1_4_002</book></page>
<page><file>A1_4_2_00381.JPG</file><book>BC_151_A1_4_002</book></page>
<page><file>A1_4_2_00382.JPG</file><book>BC_151_A1_4_002</book></page>
<page><file>A1_4_2_00383.JPG</file><book>BC_151_A1_4_002</book></page>
<page><file>A1_4_2_00384.JPG</file><book>BC_151_A1_4_002</book></page>
<page><file>A1_4_2_00385.JPG</file><book>BC_151_A1_4_002</book></page>
<page><file>A1_4_2_00386.JPG</file><book>BC_151_A1_4_002</book></page>
<page><file>A1_4_2_00387.JPG</file><book>BC_151_A1_4_002</book></page>
<page><file>A1_4_2_00388.JPG</file><book>BC_151_A1_4_002</book></page>
<page><file>A1_4_2_00389.JPG</file><book>BC_151_A1_4_002</book></page>
<page><file>A1_4_2_00390.JPG</file><book>BC_151_A1_4_002</book></page>
<page><file>A1_4_2_00421.JPG</file><book>BC_151_A1_4_002</book></page>
<page><file>A1_4_2_00422.JPG</file><book>BC_151_A1_4_002</book></page>
<page><file>A1_4_2_00423.JPG</file><book>BC_151_A1_4_002</book></page>
<page><file>A1_4_2_00424.JPG</file><book>BC_151_A1_4_002</book></page>
<page><file>A1_4_2_00425.JPG</file><book>BC_151_A1_4_002</book></page>
<page><file>A1_4_2_00426.JPG</file><book>BC_151_A1_4_002</book></page>
<page><file>A1_4_2_00427.JPG</file><book>BC_151_A1_4_002</book></page>
<page><file>A1_4_2_00428.JPG</file><book>BC_151_A1_4_002</book></page>
<page><file>A1_4_3_00429.JPG</file><book>BC_151_A1_4_003</book></page>
<page><file>A1_4_3_00430.JPG</file><book>BC_151_A1_4_003</book></page>
<page><file>A1_4_3_00431.JPG</file><book>BC_151_A1_4_003</book></page>
<page><file>A1_4_3_00432.JPG</file><book>BC_151_A1_4_003</book></page>
<page><file>A1_4_3_00433.JPG</file><book>BC_151_A1_4_003</book></page>
<page><file>A1_4_3_00434.JPG</file><book>BC_151_A1_4_003</book></page>
<page><file>A1_4_3_00435.JPG</file><book>BC_151_A1_4_003</book></page>
<page><file>A1_4_3_00436.JPG</file><book>BC_151_A1_4_003</book></page>
<page><file>A1_4_3_00437.JPG</file><book>BC_151_A1_4_003</book></page>
<page><file>A1_4_3_00438.JPG</file><book>BC_151_A1_4_003</book></page>
<page><file>A1_4_3_00439.JPG</file><book>BC_151_A1_4_003</book></page>
<page><file>A1_4_3_00440.JPG</file><book>BC_151_A1_4_003</book></page>
<page><file>A1_4_3_00441.JPG</file><book>BC_151_A1_4_003</book></page>
<page><file>A1_4_3_00442.JPG</file><book>BC_151_A1_4_003</book></page>
<page><file>A1_4_3_00443.JPG</file><book>BC_151_A1_4_003</book></page>
<page><file>A1_4_3_00444.JPG</file><book>BC_151_A1_4_003</book></page>
<page><file>A1_4_3_00445.JPG</file><book>BC_151_A1_4_003</book></page>
<page><file>A1_4_3_00446.JPG</file><book>BC_151_A1_4_003</book></page>
<page><file>A1_4_3_00447.JPG</file><book>BC_151_A1_4_003</book></page>
<page><file>A1_4_3_00448.JPG</file><book>BC_151_A1_4_003</book></page>
<page><file>A1_4_3_00449.JPG</file><book>BC_151_A1_4_003</book></page>
<page><file>A1_4_3_00450.JPG</file><book>BC_151_A1_4_003</book></page>
<page><file>A1_4_3_00451.JPG</file><book>BC_151_A1_4_003</book></page>
<page><file>A1_4_3_00452.JPG</file><book>BC_151_A1_4_003</book></page>
<page><file>A1_4_3_00453.JPG</file><book>BC_151_A1_4_003</book></page>
<page><file>A1_4_3_00454.JPG</file><book>BC_151_A1_4_003</book></page>
<page><file>A1_4_3_00455.JPG</file><book>BC_151_A1_4_003</book></page>
<page><file>A1_4_3_00456.JPG</file><book>BC_151_A1_4_003</book></page>
<page><file>A1_4_3_00457.JPG</file><book>BC_151_A1_4_003</book></page>
<page><file>A1_4_3_00458.JPG</file><book>BC_151_A1_4_003</book></page>
<page><file>A1_4_3_00459.JPG</file><book>BC_151_A1_4_003</book></page>
<page><file>A1_4_3_00460.JPG</file><book>BC_151_A1_4_003</book></page>
<page><file>A1_4_3_00501.JPG</file><book>BC_151_A1_4_003</book></page>
<page><file>A1_4_3_00502.JPG</file><book>BC_151_A1_4_003</book></page>
<page><file>A1_4_3_00503.JPG</file><book>BC_151_A1_4_003</book></page>
<page><file>A1_4_3_00504.JPG</file><book>BC_151_A1_4_003</book></page>
<page><file>A1_4_3_00505.JPG</file><book>BC_151_A1_4_003</book></page>
<page><file>A1_4_3_00506.JPG</file><book>BC_151_A1_4_003</book></page>
<page><file>A1_4_3_00507.JPG</file><book>BC_151_A1_4_003</book></page>
<page><file>A1_4_3_00508.JPG</file><book>BC_151_A1_4_003</book></page>
<page><file>A1_4_3_00509.JPG</file><book>BC_151_A1_4_003</book></page>
<page><file>A1_4_3_00510.JPG</file><book>BC_151_A1_4_003</book></page>
<page><file>A1_4_3_00511.JPG</file><book>BC_151_A1_4_003</book></page>
<page><file>A1_4_3_00512.JPG</file><book>BC_151_A1_4_003</book></page>
<page><file>A1_4_3_00513.JPG</file><book>BC_151_A1_4_003</book></page>
<page><file>A1_4_3_00514.JPG</file><book>BC_151_A1_4_003</book></page>
<page><file>A1_4_4_00515.JPG</file><book>BC_151_A1_4_004</book></page>
<page><file>A1_4_4_00516.JPG</file><book>BC_151_A1_4_004</book></page>
<page><file>A1_4_4_00517.JPG</file><book>BC_151_A1_4_004</book></page>
<page><file>A1_4_4_00518.JPG</file><book>BC_151_A1_4_004</book></page>
<page><file>A1_4_4_00519.JPG</file><book>BC_151_A1_4_004</book></page>
<page><file>A1_4_4_00520.JPG</file><book>BC_151_A1_4_004</book></page>
<page><file>A1_4_4_00521.JPG</file><book>BC_151_A1_4_004</book></page>
<page><file>A1_4_4_00522.JPG</file><book>BC_151_A1_4_004</book></page>
<page><file>A1_4_4_00523.JPG</file><book>BC_151_A1_4_004</book></page>
<page><file>A1_4_4_00524.JPG</file><book>BC_151_A1_4_004</book></page>
<page><file>A1_4_4_00525.JPG</file><book>BC_151_A1_4_004</book></page>
<page><file>A1_4_4_00526.JPG</file><book>BC_151_A1_4_004</book></page>
<page><file>A1_4_4_00528.JPG</file><book>BC_151_A1_4_004</book></page>
<page><file>A1_4_4_00529.JPG</file><book>BC_151_A1_4_004</book></page>
<page><file>A1_4_4_00530.JPG</file><book>BC_151_A1_4_004</book></page>
<page><file>A1_4_4_00531.JPG</file><book>BC_151_A1_4_004</book></page>
<page><file>A1_4_4_00532.JPG</file><book>BC_151_A1_4_004</book></page>
<page><file>A1_4_4_00533.JPG</file><book>BC_151_A1_4_004</book></page>
<page><file>A1_4_4_00534.JPG</file><book>BC_151_A1_4_004</book></page>
<page><file>A1_4_4_00535.JPG</file><book>BC_151_A1_4_004</book></page>
<page><file>A1_4_4_00536.JPG</file><book>BC_151_A1_4_004</book></page>
<page><file>A1_4_4_00537.JPG</file><book>BC_151_A1_4_004</book></page>
<page><file>A1_4_4_00538.JPG</file><book>BC_151_A1_4_004</book></page>
<page><file>A1_4_4_00539.JPG</file><book>BC_151_A1_4_004</book></page>
<page><file>A1_4_4_00540.JPG</file><book>BC_151_A1_4_004</book></page>
<page><file>A1_4_4_00541.JPG</file><book>BC_151_A1_4_004</book></page>
<page><file>A1_4_4_00542.JPG</file><book>BC_151_A1_4_004</book></page>
<page><file>A1_4_4_00543.JPG</file><book>BC_151_A1_4_004</book></page>
<page><file>A1_4_4_00544.JPG</file><book>BC_151_A1_4_004</book></page>
<page><file>A1_4_4_00545.JPG</file><book>BC_151_A1_4_004</book></page>
<page><file>A1_4_4_00546.JPG</file><book>BC_151_A1_4_004</book></page>
<page><file>A1_4_4_00547.JPG</file><book>BC_151_A1_4_004</book></page>
<page><file>A1_4_4_00548.JPG</file><book>BC_151_A1_4_004</book></page>
<page><file>A1_4_4_00549.JPG</file><book>BC_151_A1_4_004</book></page>
<page><file>A1_4_4_00550.JPG</file><book>BC_151_A1_4_004</book></page>
<page><file>A1_4_4_00551.JPG</file><book>BC_151_A1_4_004</book></page>
<page><file>A1_4_4_00552.JPG</file><book>BC_151_A1_4_004</book></page>
<page><file>A1_4_4_00553.JPG</file><book>BC_151_A1_4_004</book></page>
<page><file>A1_4_4_00554.JPG</file><book>BC_151_A1_4_004</book></page>
<page><file>A1_4_4_00555.JPG</file><book>BC_151_A1_4_004</book></page>
<page><file>A1_4_4_00556.JPG</file><book>BC_151_A1_4_004</book></page>
<page><file>A1_4_4_00557.JPG</file><book>BC_151_A1_4_004</book></page>
<page><file>A1_4_4_00558.JPG</file><book>BC_151_A1_4_004</book></page>
<page><file>A1_4_4_00559.JPG</file><book>BC_151_A1_4_004</book></page>
<page><file>A1_4_4_00560.JPG</file><book>BC_151_A1_4_004</book></page>
<page><file>A1_4_4_00561.JPG</file><book>BC_151_A1_4_004</book></page>
<page><file>A1_4_4_00562.JPG</file><book>BC_151_A1_4_004</book></page>
<page><file>A1_4_4_00563.JPG</file><book>BC_151_A1_4_004</book></page>
<page><file>A1_4_4_00564.JPG</file><book>BC_151_A1_4_004</book></page>
<page><file>A1_4_4_00565.JPG</file><book>BC_151_A1_4_004</book></page>
<page><file>A1_4_4_00566.JPG</file><book>BC_151_A1_4_004</book></page>
<page><file>A1_4_4_00567.JPG</file><book>BC_151_A1_4_004</book></page>
<page><file>A1_4_4_00568.JPG</file><book>BC_151_A1_4_004</book></page>
<page><file>A1_4_4_00569.JPG</file><book>BC_151_A1_4_004</book></page>
<page><file>A1_4_4_00570.JPG</file><book>BC_151_A1_4_004</book></page>
<page><file>A1_4_4_00571.JPG</file><book>BC_151_A1_4_004</book></page>
<page><file>A1_4_4_00572.JPG</file><book>BC_151_A1_4_004</book></page>
<page><file>A1_4_4_00573.JPG</file><book>BC_151_A1_4_004</book></page>
<page><file>A1_4_4_00574.JPG</file><book>BC_151_A1_4_004</book></page>
<page><file>A1_4_4_00575.JPG</file><book>BC_151_A1_4_004</book></page>
<page><file>A1_4_4_00576.JPG</file><book>BC_151_A1_4_004</book></page>
<page><file>A1_4_4_00577.JPG</file><book>BC_151_A1_4_004</book></page>
<page><file>A1_4_4_00578.JPG</file><book>BC_151_A1_4_004</book></page>
<page><file>A1_4_4_00579.JPG</file><book>BC_151_A1_4_004</book></page>
<page><file>A1_4_4_00580.JPG</file><book>BC_151_A1_4_004</book></page>
<page><file>A1_4_4_00581.JPG</file><book>BC_151_A1_4_004</book></page>
<page><file>A1_4_4_00582.JPG</file><book>BC_151_A1_4_004</book></page>
<page><file>A1_4_4_00583.JPG</file><book>BC_151_A1_4_004</book></page>
<page><file>A1_4_4_00584.JPG</file><book>BC_151_A1_4_004</book></page>
<page><file>A1_4_5_00585.JPG</file><book>BC_151_A1_4_005</book></page>
<page><file>A1_4_5_00586.JPG</file><book>BC_151_A1_4_005</book></page>
<page><file>A1_4_5_00587.JPG</file><book>BC_151_A1_4_005</book></page>
<page><file>A1_4_5_00588.JPG</file><book>BC_151_A1_4_005</book></page>
<page><file>A1_4_5_00589.JPG</file><book>BC_151_A1_4_005</book></page>
<page><file>A1_4_5_00590.JPG</file><book>BC_151_A1_4_005</book></page>
<page><file>A1_4_16_01497.JPG</file><book>BC_151_A1_4_016</book></page>
<page><file>A1_4_16_01498.JPG</file><book>BC_151_A1_4_016</book></page>
<page><file>A1_4_16_01499.JPG</file><book>BC_151_A1_4_016</book></page>
<page><file>A1_4_16_01500.JPG</file><book>BC_151_A1_4_016</book></page>
<page><file>A1_4_16_01501.JPG</file><book>BC_151_A1_4_016</book></page>
<page><file>A1_4_16_01502.JPG</file><book>BC_151_A1_4_016</book></page>
<page><file>A1_4_16_01503.JPG</file><book>BC_151_A1_4_016</book></page>
<page><file>A1_4_16_01504.JPG</file><book>BC_151_A1_4_016</book></page>
<page><file>A1_4_16_01505.JPG</file><book>BC_151_A1_4_016</book></page>
<page><file>A1_4_16_01506.JPG</file><book>BC_151_A1_4_016</book></page>
<page><file>A1_4_16_01507.JPG</file><book>BC_151_A1_4_016</book></page>
<page><file>A1_4_16_01508.JPG</file><book>BC_151_A1_4_016</book></page>
<page><file>A1_4_16_01509.JPG</file><book>BC_151_A1_4_016</book></page>
<page><file>A1_4_16_01510.JPG</file><book>BC_151_A1_4_016</book></page>
<page><file>A1_4_16_01511.JPG</file><book>BC_151_A1_4_016</book></page>
<page><file>A1_4_16_01512.JPG</file><book>BC_151_A1_4_016</book></page>
<page><file>A1_4_16_01513.JPG</file><book>BC_151_A1_4_016</book></page>
<page><file>A1_4_16_01514.JPG</file><book>BC_151_A1_4_016</book></page>
<page><file>A1_4_16_01515.JPG</file><book>BC_151_A1_4_016</book></page>
<page><file>A1_4_16_01516.JPG</file><book>BC_151_A1_4_016</book></page>
<page><file>A1_4_16_01517.JPG</file><book>BC_151_A1_4_016</book></page>
<page><file>A1_4_16_01518.JPG</file><book>BC_151_A1_4_016</book></page>
<page><file>A1_4_16_01519.JPG</file><book>BC_151_A1_4_016</book></page>
<page><file>A1_4_16_01520.JPG</file><book>BC_151_A1_4_016</book></page>
<page><file>A1_4_16_01521.JPG</file><book>BC_151_A1_4_016</book></page>
<page><file>A1_4_16_01522.JPG</file><book>BC_151_A1_4_016</book></page>
<page><file>A1_4_16_01523.JPG</file><book>BC_151_A1_4_016</book></page>
<page><file>A1_4_16_01524.JPG</file><book>BC_151_A1_4_016</book></page>
<page><file>A1_4_16_01525.JPG</file><book>BC_151_A1_4_016</book></page>
<page><file>A1_4_16_01526.JPG</file><book>BC_151_A1_4_016</book></page>
<page><file>A1_4_16_01527.JPG</file><book>BC_151_A1_4_016</book></page>
<page><file>A1_4_16_01528.JPG</file><book>BC_151_A1_4_016</book></page>
<page><file>A1_4_16_01529.JPG</file><book>BC_151_A1_4_016</book></page>
<page><file>A1_4_16_01530.JPG</file><book>BC_151_A1_4_016</book></page>
<page><file>A1_4_16_01531.JPG</file><book>BC_151_A1_4_016</book></page>
<page><file>A1_4_16_01532.JPG</file><book>BC_151_A1_4_016</book></page>
<page><file>A1_4_16_01533.JPG</file><book>BC_151_A1_4_016</book></page>
<page><file>A1_4_16_01534.JPG</file><book>BC_151_A1_4_016</book></page>
<page><file>A1_4_16_01535.JPG</file><book>BC_151_A1_4_016</book></page>
<page><file>A1_4_16_01536.JPG</file><book>BC_151_A1_4_016</book></page>
<page><file>A1_4_16_01537.JPG</file><book>BC_151_A1_4_016</book></page>
<page><file>A1_4_16_01538.JPG</file><book>BC_151_A1_4_016</book></page>
<page><file>A1_4_16_01539.JPG</file><book>BC_151_A1_4_016</book></page>
<page><file>A1_4_16_01540.JPG</file><book>BC_151_A1_4_016</book></page>
<page><file>A1_4_16_01541.JPG</file><book>BC_151_A1_4_016</book></page>
<page><file>A1_4_16_01542.JPG</file><book>BC_151_A1_4_016</book></page>
<page><file>A1_4_16_01543.JPG</file><book>BC_151_A1_4_016</book></page>
<page><file>A1_4_16_01544.JPG</file><book>BC_151_A1_4_016</book></page>
<page><file>A1_4_16_01545.JPG</file><book>BC_151_A1_4_016</book></page>
<page><file>A1_4_16_01546.JPG</file><book>BC_151_A1_4_016</book></page>
<page><file>A1_4_16_01547.JPG</file><book>BC_151_A1_4_016</book></page>
<page><file>A1_4_16_01548.JPG</file><book>BC_151_A1_4_016</book></page>
<page><file>A1_4_16_01549.JPG</file><book>BC_151_A1_4_016</book></page>
<page><file>A1_4_16_01550.JPG</file><book>BC_151_A1_4_016</book></page>
<page><file>A1_4_16_01551.JPG</file><book>BC_151_A1_4_016</book></page>
<page><file>A1_4_16_01552.JPG</file><book>BC_151_A1_4_016</book></page>
<page><file>A1_4_16_01553.JPG</file><book>BC_151_A1_4_016</book></page>
<page><file>A1_4_16_01554.JPG</file><book>BC_151_A1_4_016</book></page>
<page><file>A1_4_16_01555.JPG</file><book>BC_151_A1_4_016</book></page>
<page><file>A1_4_16_01556.JPG</file><book>BC_151_A1_4_016</book></page>
<page><file>A1_4_16_01557.JPG</file><book>BC_151_A1_4_016</book></page>
<page><file>A1_4_16_01558.JPG</file><book>BC_151_A1_4_016</book></page>
<page><file>A1_4_16_01559.JPG</file><book>BC_151_A1_4_016</book></page>
<page><file>A1_4_16_01560.JPG</file><book>BC_151_A1_4_016</book></page>
<page><file>A1_4_16_01561.JPG</file><book>BC_151_A1_4_016</book></page>
<page><file>A1_4_16_01562.JPG</file><book>BC_151_A1_4_016</book></page>
<page><file>A1_4_16_01563.JPG</file><book>BC_151_A1_4_016</book></page>
<page><file>A1_4_16_01564.JPG</file><book>BC_151_A1_4_016</book></page>
<page><file>A1_4_16_01565.JPG</file><book>BC_151_A1_4_016</book></page>
<page><file>A1_4_16_01566.JPG</file><book>BC_151_A1_4_016</book></page>
<page><file>A1_4_16_01567.JPG</file><book>BC_151_A1_4_016</book></page>
<page><file>A1_4_16_01568.JPG</file><book>BC_151_A1_4_016</book></page>
<page><file>A1_4_16_01569.JPG</file><book>BC_151_A1_4_016</book></page>
<page><file>A1_4_16_01570.JPG</file><book>BC_151_A1_4_016</book></page>
<page><file>A1_4_16_01571.JPG</file><book>BC_151_A1_4_016</book></page>
<page><file>A1_4_16_01572.JPG</file><book>BC_151_A1_4_016</book></page>
<page><file>A1_4_16_01573.JPG</file><book>BC_151_A1_4_016</book></page>
<page><file>A1_4_16_01574.JPG</file><book>BC_151_A1_4_016</book></page>
<page><file>A1_4_16_01575.JPG</file><book>BC_151_A1_4_016</book></page>
<page><file>A1_4_16_01576.JPG</file><book>BC_151_A1_4_016</book></page>
<page><file>A1_4_16_01577.JPG</file><book>BC_151_A1_4_016</book></page>
<page><file>A1_4_16_01578.JPG</file><book>BC_151_A1_4_016</book></page>
<page><file>A1_4_16_01579.JPG</file><book>BC_151_A1_4_016</book></page>
<page><file>A1_4_16_01580.JPG</file><book>BC_151_A1_4_016</book></page>
<page><file>A1_4_16_01581.JPG</file><book>BC_151_A1_4_016</book></page>
<page><file>A1_4_16_01582.JPG</file><book>BC_151_A1_4_016</book></page>
<page><file>A1_4_16_01583.JPG</file><book>BC_151_A1_4_016</book></page>
<page><file>A1_4_16_01584.JPG</file><book>BC_151_A1_4_016</book></page>
<page><file>A1_4_16_01585.JPG</file><book>BC_151_A1_4_016</book></page>
<page><file>A1_4_16_01586.JPG</file><book>BC_151_A1_4_016</book></page>
<page><file>A1_4_16_01587.JPG</file><book>BC_151_A1_4_016</book></page>
<page><file>A1_4_16_01588.JPG</file><book>BC_151_A1_4_016</book></page>
<page><file>A1_4_16_01589.JPG</file><book>BC_151_A1_4_016</book></page>
<page><file>A1_4_16_01590.JPG</file><book>BC_151_A1_4_016</book></page>
<page><file>A1_4_17_01591.JPG</file><book>BC_151_A1_4_017</book></page>
<page><file>A1_4_17_01592.JPG</file><book>BC_151_A1_4_017</book></page>
<page><file>A1_4_17_01593.JPG</file><book>BC_151_A1_4_017</book></page>
<page><file>A1_4_17_01594.JPG</file><book>BC_151_A1_4_017</book></page>
<page><file>A1_4_17_01595.JPG</file><book>BC_151_A1_4_017</book></page>
<page><file>A1_4_17_01596.JPG</file><book>BC_151_A1_4_017</book></page>
<page><file>A1_4_17_01597.JPG</file><book>BC_151_A1_4_017</book></page>
<page><file>A1_4_17_01598.JPG</file><book>BC_151_A1_4_017</book></page>
<page><file>A1_4_17_01599.JPG</file><book>BC_151_A1_4_017</book></page>
<page><file>A1_4_17_01600.JPG</file><book>BC_151_A1_4_017</book></page>
<page><file>A1_4_17_01601.JPG</file><book>BC_151_A1_4_017</book></page>
<page><file>A1_4_17_01602.JPG</file><book>BC_151_A1_4_017</book></page>
<page><file>A1_4_17_01603.JPG</file><book>BC_151_A1_4_017</book></page>
<page><file>A1_4_17_01604.JPG</file><book>BC_151_A1_4_017</book></page>
<page><file>A1_4_17_01605.JPG</file><book>BC_151_A1_4_017</book></page>
<page><file>A1_4_17_01606.JPG</file><book>BC_151_A1_4_017</book></page>
<page><file>A1_4_17_01607.JPG</file><book>BC_151_A1_4_017</book></page>
<page><file>A1_4_17_01608.JPG</file><book>BC_151_A1_4_017</book></page>
<page><file>A1_4_17_01609.JPG</file><book>BC_151_A1_4_017</book></page>
<page><file>A1_4_17_01610.JPG</file><book>BC_151_A1_4_017</book></page>
<page><file>A1_4_17_01611.JPG</file><book>BC_151_A1_4_017</book></page>
<page><file>A1_4_17_01612.JPG</file><book>BC_151_A1_4_017</book></page>
<page><file>A1_4_17_01613.JPG</file><book>BC_151_A1_4_017</book></page>
<page><file>A1_4_17_01614.JPG</file><book>BC_151_A1_4_017</book></page>
<page><file>A1_4_17_01615.JPG</file><book>BC_151_A1_4_017</book></page>
<page><file>A1_4_17_01616.JPG</file><book>BC_151_A1_4_017</book></page>
<page><file>A1_4_17_01617.JPG</file><book>BC_151_A1_4_017</book></page>
<page><file>A1_4_17_01618.JPG</file><book>BC_151_A1_4_017</book></page>
<page><file>A1_4_17_01619.JPG</file><book>BC_151_A1_4_017</book></page>
<page><file>A1_4_17_01620.JPG</file><book>BC_151_A1_4_017</book></page>
<page><file>A1_4_17_01621.JPG</file><book>BC_151_A1_4_017</book></page>
<page><file>A1_4_17_01622.JPG</file><book>BC_151_A1_4_017</book></page>
<page><file>A1_4_17_01623.JPG</file><book>BC_151_A1_4_017</book></page>
<page><file>A1_4_17_01624.JPG</file><book>BC_151_A1_4_017</book></page>
<page><file>A1_4_17_01625.JPG</file><book>BC_151_A1_4_017</book></page>
<page><file>A1_4_17_01626.JPG</file><book>BC_151_A1_4_017</book></page>
<page><file>A1_4_17_01627.JPG</file><book>BC_151_A1_4_017</book></page>
<page><file>A1_4_17_01628.JPG</file><book>BC_151_A1_4_017</book></page>
<page><file>A1_4_17_01629.JPG</file><book>BC_151_A1_4_017</book></page>
<page><file>A1_4_17_01630.JPG</file><book>BC_151_A1_4_017</book></page>
<page><file>A1_4_17_01631.JPG</file><book>BC_151_A1_4_017</book></page>
<page><file>A1_4_17_01632.JPG</file><book>BC_151_A1_4_017</book></page>
<page><file>A1_4_17_01633.JPG</file><book>BC_151_A1_4_017</book></page>
<page><file>A1_4_17_01634.JPG</file><book>BC_151_A1_4_017</book></page>
<page><file>A1_4_17_01635.JPG</file><book>BC_151_A1_4_017</book></page>
<page><file>A1_4_17_01636.JPG</file><book>BC_151_A1_4_017</book></page>
<page><file>A1_4_17_01637.JPG</file><book>BC_151_A1_4_017</book></page>
<page><file>A1_4_17_01638.JPG</file><book>BC_151_A1_4_017</book></page>
<page><file>A1_4_17_01639.JPG</file><book>BC_151_A1_4_017</book></page>
<page><file>A1_4_17_01640.JPG</file><book>BC_151_A1_4_017</book></page>
<page><file>A1_4_17_01641.JPG</file><book>BC_151_A1_4_017</book></page>
<page><file>A1_4_17_01642.JPG</file><book>BC_151_A1_4_017</book></page>
<page><file>A1_4_17_01643.JPG</file><book>BC_151_A1_4_017</book></page>
<page><file>A1_4_17_01644.JPG</file><book>BC_151_A1_4_017</book></page>
<page><file>A1_4_17_01645.JPG</file><book>BC_151_A1_4_017</book></page>
<page><file>A1_4_17_01646.JPG</file><book>BC_151_A1_4_017</book></page>
<page><file>A1_4_17_01647.JPG</file><book>BC_151_A1_4_017</book></page>
<page><file>A1_4_17_01648.JPG</file><book>BC_151_A1_4_017</book></page>
<page><file>A1_4_17_01649.JPG</file><book>BC_151_A1_4_017</book></page>
<page><file>A1_4_17_01650.JPG</file><book>BC_151_A1_4_017</book></page>
<page><file>A1_4_17_01651.JPG</file><book>BC_151_A1_4_017</book></page>
<page><file>A1_4_17_01652.JPG</file><book>BC_151_A1_4_017</book></page>
<page><file>A1_4_17_01653.JPG</file><book>BC_151_A1_4_017</book></page>
<page><file>A1_4_17_01654.JPG</file><book>BC_151_A1_4_017</book></page>
<page><file>A1_4_17_01655.JPG</file><book>BC_151_A1_4_017</book></page>
<page><file>A1_4_17_01656.JPG</file><book>BC_151_A1_4_017</book></page>
<page><file>A1_4_17_01657.JPG</file><book>BC_151_A1_4_017</book></page>
<page><file>A1_4_17_01658.JPG</file><book>BC_151_A1_4_017</book></page>
<page><file>A1_4_17_01659.JPG</file><book>BC_151_A1_4_017</book></page>
<page><file>A1_4_17_01660.JPG</file><book>BC_151_A1_4_017</book></page>
<page><file>A1_4_17_01661.JPG</file><book>BC_151_A1_4_017</book></page>
<page><file>A1_4_17_01662.JPG</file><book>BC_151_A1_4_017</book></page>
<page><file>A1_4_17_01663.JPG</file><book>BC_151_A1_4_017</book></page>
<page><file>A1_4_17_01664.JPG</file><book>BC_151_A1_4_017</book></page>
<page><file>A1_4_17_01665.JPG</file><book>BC_151_A1_4_017</book></page>
<page><file>A1_4_17_01666.JPG</file><book>BC_151_A1_4_017</book></page>
<page><file>A1_4_17_01667.JPG</file><book>BC_151_A1_4_017</book></page>
<page><file>A1_4_17_01668.JPG</file><book>BC_151_A1_4_017</book></page>
<page><file>A1_4_17_01669.JPG</file><book>BC_151_A1_4_017</book></page>
<page><file>A1_4_17_01670.JPG</file><book>BC_151_A1_4_017</book></page>
<page><file>A1_4_17_01671.JPG</file><book>BC_151_A1_4_017</book></page>
<page><file>A1_4_17_01672.JPG</file><book>BC_151_A1_4_017</book></page>
<page><file>A1_4_17_01673.JPG</file><book>BC_151_A1_4_017</book></page>
<page><file>A1_4_17_01674.JPG</file><book>BC_151_A1_4_017</book></page>
<page><file>A1_4_17_01675.JPG</file><book>BC_151_A1_4_017</book></page>
<page><file>A1_4_17_01676.JPG</file><book>BC_151_A1_4_017</book></page>
<page><file>A1_4_17_01677.JPG</file><book>BC_151_A1_4_017</book></page>
<page><file>A1_4_17_01678.JPG</file><book>BC_151_A1_4_017</book></page>
<page><file>A1_4_17_01679.JPG</file><book>BC_151_A1_4_017</book></page>
<page><file>A1_4_17_01680.JPG</file><book>BC_151_A1_4_017</book></page>
<page><file>A1_4_17_01681.JPG</file><book>BC_151_A1_4_017</book></page>
<page><file>A1_4_17_01682.JPG</file><book>BC_151_A1_4_017</book></page>
<page><file>A1_4_17_01683.JPG</file><book>BC_151_A1_4_017</book></page>
<page><file>A1_4_18_01698.JPG</file><book>BC_151_A1_4_018</book></page>
<page><file>A1_4_18_01699.JPG</file><book>BC_151_A1_4_018</book></page>
<page><file>A1_4_18_01700.JPG</file><book>BC_151_A1_4_018</book></page>
<page><file>A1_4_18_01701.JPG</file><book>BC_151_A1_4_018</book></page>
<page><file>A1_4_18_01702.JPG</file><book>BC_151_A1_4_018</book></page>
<page><file>A1_4_18_01703.JPG</file><book>BC_151_A1_4_018</book></page>
<page><file>A1_4_18_01704.JPG</file><book>BC_151_A1_4_018</book></page>
<page><file>A1_4_18_01705.JPG</file><book>BC_151_A1_4_018</book></page>
<page><file>A1_4_18_01706.JPG</file><book>BC_151_A1_4_018</book></page>
<page><file>A1_4_18_01707.JPG</file><book>BC_151_A1_4_018</book></page>
<page><file>A1_4_18_01708.JPG</file><book>BC_151_A1_4_018</book></page>
<page><file>A1_4_18_01709.JPG</file><book>BC_151_A1_4_018</book></page>
<page><file>A1_4_18_01710.JPG</file><book>BC_151_A1_4_018</book></page>
<page><file>A1_4_18_01711.JPG</file><book>BC_151_A1_4_018</book></page>
<page><file>A1_4_18_01725.JPG</file><book>BC_151_A1_4_018</book></page>
<page><file>A1_4_18_01726.JPG</file><book>BC_151_A1_4_018</book></page>
<page><file>A1_4_18_01727.JPG</file><book>BC_151_A1_4_018</book></page>
<page><file>A1_4_18_01728.JPG</file><book>BC_151_A1_4_018</book></page>
<page><file>A1_4_18_01729.JPG</file><book>BC_151_A1_4_018</book></page>
<page><file>A1_4_18_01730.JPG</file><book>BC_151_A1_4_018</book></page>
<page><file>A1_4_18_01731.JPG</file><book>BC_151_A1_4_018</book></page>
<page><file>A1_4_18_01732.JPG</file><book>BC_151_A1_4_018</book></page>
<page><file>A1_4_18_01733.JPG</file><book>BC_151_A1_4_018</book></page>
<page><file>A1_4_18_01734.JPG</file><book>BC_151_A1_4_018</book></page>
<page><file>A1_4_18_01735.JPG</file><book>BC_151_A1_4_018</book></page>
<page><file>A1_4_18_01736.JPG</file><book>BC_151_A1_4_018</book></page>
<page><file>A1_4_18_01737.JPG</file><book>BC_151_A1_4_018</book></page>
<page><file>A1_4_18_01738.JPG</file><book>BC_151_A1_4_018</book></page>
<page><file>A1_4_18_01739.JPG</file><book>BC_151_A1_4_018</book></page>
<page><file>A1_4_18_01740.JPG</file><book>BC_151_A1_4_018</book></page>
<page><file>A1_4_18_01741.JPG</file><book>BC_151_A1_4_018</book></page>
<page><file>A1_4_18_01742.JPG</file><book>BC_151_A1_4_018</book></page>
<page><file>A1_4_18_01743.JPG</file><book>BC_151_A1_4_018</book></page>
<page><file>A1_4_18_01744.JPG</file><book>BC_151_A1_4_018</book></page>
<page><file>A1_4_18_01745.JPG</file><book>BC_151_A1_4_018</book></page>
<page><file>A1_4_18_01746.JPG</file><book>BC_151_A1_4_018</book></page>
<page><file>A1_4_18_01747.JPG</file><book>BC_151_A1_4_018</book></page>
<page><file>A1_4_18_01748.JPG</file><book>BC_151_A1_4_018</book></page>
<page><file>A1_4_18_01749.JPG</file><book>BC_151_A1_4_018</book></page>
<page><file>A1_4_18_01750.JPG</file><book>BC_151_A1_4_018</book></page>
<page><file>A1_4_18_01751.JPG</file><book>BC_151_A1_4_018</book></page>
<page><file>A1_4_18_01752.JPG</file><book>BC_151_A1_4_018</book></page>
<page><file>A1_4_18_01753.JPG</file><book>BC_151_A1_4_018</book></page>
<page><file>A1_4_18_01754.JPG</file><book>BC_151_A1_4_018</book></page>
<page><file>A1_4_18_01755.JPG</file><book>BC_151_A1_4_018</book></page>
<page><file>A1_4_18_01756.JPG</file><book>BC_151_A1_4_018</book></page>
<page><file>A1_4_18_01757.JPG</file><book>BC_151_A1_4_018</book></page>
<page><file>A1_4_18_01758.JPG</file><book>BC_151_A1_4_018</book></page>
</item>
